Metadata-Version: 2.4
Name: openai-agents-python-vdomina
Version: 0.6.6.1
Summary: OpenAI Agents SDK (fork with emit_event support)
Project-URL: Homepage, https://openai.github.io/openai-agents-python/
Project-URL: Repository, https://github.com/vincenzodomina/openai-agents-python
Author-email: vincenzodomina <vincenzo.domina@googlemail.com>
License-Expression: MIT
License-File: LICENSE
Classifier: Intended Audience :: Developers
Classifier: License :: OSI Approved :: MIT License
Classifier: Operating System :: OS Independent
Classifier: Programming Language :: Python :: 3
Classifier: Programming Language :: Python :: 3.9
Classifier: Programming Language :: Python :: 3.10
Classifier: Programming Language :: Python :: 3.11
Classifier: Programming Language :: Python :: 3.12
Classifier: Programming Language :: Python :: 3.13
Classifier: Programming Language :: Python :: 3.14
Classifier: Topic :: Software Development :: Libraries :: Python Modules
Classifier: Typing :: Typed
Requires-Python: >=3.9
Requires-Dist: griffe<2,>=1.5.6
Requires-Dist: mcp<2,>=1.11.0; python_version >= '3.10'
Requires-Dist: openai<3,>=2.9.0
Requires-Dist: pydantic<3,>=2.12.3
Requires-Dist: requests<3,>=2.0
Requires-Dist: types-requests<3,>=2.0
Requires-Dist: typing-extensions<5,>=4.12.2
Provides-Extra: dapr
Requires-Dist: dapr>=1.16.0; extra == 'dapr'
Requires-Dist: grpcio>=1.60.0; extra == 'dapr'
Provides-Extra: encrypt
Requires-Dist: cryptography<46,>=45.0; extra == 'encrypt'
Provides-Extra: litellm
Requires-Dist: litellm<2,>=1.80.10; extra == 'litellm'
Provides-Extra: realtime
Requires-Dist: websockets<16,>=15.0; extra == 'realtime'
Provides-Extra: redis
Requires-Dist: redis>=7; extra == 'redis'
Provides-Extra: sqlalchemy
Requires-Dist: asyncpg>=0.29.0; extra == 'sqlalchemy'
Requires-Dist: sqlalchemy>=2.0; extra == 'sqlalchemy'
Provides-Extra: viz
Requires-Dist: graphviz>=0.17; extra == 'viz'
Provides-Extra: voice
Requires-Dist: numpy<3,>=2.2.0; (python_version >= '3.10') and extra == 'voice'
Requires-Dist: websockets<16,>=15.0; extra == 'voice'
